cmem_plugin_csvcombine/__init__.py
cmem_plugin_csvcombine/lsicon--file-csv-outline.svg
cmem_plugin_csvcombine/plugin_csvcombine.py
cmem_plugin_csvcombine-3.2.0.dist-info/METADATA
cmem_plugin_csvcombine-3.2.0.dist-info/WHEEL
cmem_plugin_csvcombine-3.2.0.dist-info/licenses/LICENSE
cmem_plugin_csvcombine-3.2.0.dist-info/RECORD
